tabel/__init__.py
tabel/_version.py
tabel/git_version.py
tabel/hashjoin.py
tabel/numpy_types.py
tabel/tabel.py
tabel/util.py
tabel-1.2.1.dist-info/METADATA
tabel-1.2.1.dist-info/RECORD
tabel-1.2.1.dist-info/WHEEL
tabel-1.2.1.dist-info/top_level.txt
