Metadata-Version: 2.1
Name: tabel
Version: 1.2.1
Summary: Lightweight, intuitive and fast data-tables.
Home-page: https://github.com/BastiaanBergman/tabel
Author: Bastiaan Bergman
Author-email: Bastiaan.Bergman@gmail.com
License: MIT
Project-URL: Documentation, https://tabel.readthedocs.io/en/stable/
Project-URL: Source Code, https://github.com/BastiaanBergman/tabel
Keywords: data table
Platform: UNKNOWN
Classifier: Programming Language :: Python :: 3
Classifier: Programming Language :: Python :: 3.6
Classifier: Programming Language :: Python :: 2
Classifier: Programming Language :: Python :: 2.7
Classifier: License :: OSI Approved :: MIT License
Classifier: Operating System :: OS Independent
Requires-Python: >=2.6, >=3.0
Requires-Dist: numpy
Requires-Dist: tabulate
